anekos/__init__.py
anekos/client.py
anekos/enumeration.py
anekos/errors.py
anekos/http_client.py
anekos/result.py
anekos.py-2.0.0.dist-info/LICENSE
anekos.py-2.0.0.dist-info/METADATA
anekos.py-2.0.0.dist-info/WHEEL
anekos.py-2.0.0.dist-info/top_level.txt
anekos.py-2.0.0.dist-info/RECORD
